{
  "number": 32,
  "verses": [
    {
      "number": 1,
      "text1637": "HEBBEN zij u tot een overste gesteld, verhef u niet, maar wees bij hen als een van henlieden.",
      "textSV1888": "HEBBEN zij u tot een overste gesteld, verhef u niet, maar wees bij hen als een van henlieden.",
      "text2026": "HEBBEN zij u tot een overste gesteld, verhef u niet, maar wees bij hen als één van henlieden.",
      "marginNotes": [],
      "text2026_html": "HEBBEN zij u tot een overste gesteld, verhef u niet, maar wees bij hen als één van henlieden.",
      "phraseDiff": [
        {
          "old": "een",
          "new": "één",
          "principe": null
        }
      ],
      "grondtekst": [
        {
          "woord": "ηγεομαι",
          "lemma": "ἡγέομαι"
        },
        {
          "woord": "σε.1",
          "lemma": "σέ"
        },
        {
          "woord": "καθιστημι",
          "lemma": "καθίστημι"
        },
        {
          "woord": "μη",
          "lemma": "μή"
        },
        {
          "woord": "επαιρω",
          "lemma": "ἐπαίρω"
        },
        {
          "woord": "γινομαι",
          "lemma": "γίνομαι"
        },
        {
          "woord": "εν",
          "lemma": "ἐν"
        },
        {
          "woord": "αυτος",
          "lemma": "αὐτός"
        },
        {
          "woord": "ως.1",
          "lemma": "ὥς"
        },
        {
          "woord": "εις.1",
          "lemma": "εἷς"
        },
        {
          "woord": "εκ",
          "lemma": "ἐκ"
        },
        {
          "woord": "αυτος",
          "lemma": "αὐτός"
        },
        {
          "woord": "φροντιζω",
          "lemma": "φροντίζω"
        },
        {
          "woord": "αυτος",
          "lemma": "αὐτός"
        },
        {
          "woord": "και",
          "lemma": "καί"
        },
        {
          "woord": "ουτως",
          "lemma": "οὕτως"
        },
        {
          "woord": "καθιζω",
          "lemma": "καθίζω"
        }
      ]
    },
    {
      "number": 2,
      "text1637": "Bezorg hen, en zet u zo neder.",
      "textSV1888": "Bezorg hen, en zet u zo neder.",
      "text2026": "Bezorg hen, en zet u zo neder.",
      "marginNotes": [],
      "text2026_html": "Bezorg hen, en zet u zo neder.",
      "grondtekst": [
        {
          "woord": "και",
          "lemma": "καί"
        },
        {
          "woord": "πας",
          "lemma": "πᾶς"
        },
        {
          "woord": "ο",
          "lemma": "ὁ"
        },
        {
          "woord": "χρεια",
          "lemma": "χρεία"
        },
        {
          "woord": "σου",
          "lemma": "σοῦ"
        },
        {
          "woord": "ποιεω",
          "lemma": "ποιέω"
        },
        {
          "woord": "αναπιπτω",
          "lemma": "ἀναπίπτω"
        },
        {
          "woord": "ινα",
          "lemma": "ἵνα"
        },
        {
          "woord": "ευφραινω",
          "lemma": "εὐφραίνω"
        },
        {
          "woord": "δια",
          "lemma": "διά"
        },
        {
          "woord": "αυτος",
          "lemma": "αὐτός"
        },
        {
          "woord": "και",
          "lemma": "καί"
        },
        {
          "woord": "ευκοσμια",
          "lemma": "εὐκοσμία"
        },
        {
          "woord": "χαρις",
          "lemma": "χάρις"
        },
        {
          "woord": "λαμβανω",
          "lemma": "λαμβάνω"
        },
        {
          "woord": "στεφανος.1",
          "lemma": "στέφανος"
        }
      ]
    },
    {
      "number": 3,
      "text1637": "En doe al wat nodig is te doen, en als gij zult geprezen zijn, zo rust, opdat gij van hunnentwege verheugd zijt, en om wel versierd te wezen een kroon moogt ontvangen.",
      "textSV1888": "En doe al wat nodig is te doen, en als gij zult geprezen zijn, zo rust, opdat gij van hunnentwege verheugd zijt, en om wel versierd te wezen een kroon moogt ontvangen.",
      "text2026": "En doe al wat nodig is te doen, en als u zult geprezen zijn, zo rust, opdat u van hunnentwege verheugd bent, en om wel versierd te wezen een kroon moogt ontvangen.",
      "marginNotes": [],
      "text2026_html": "En doe al wat nodig is te doen, en als u zult geprezen zijn, zo rust, opdat u van hunnentwege verheugd bent, en om wel versierd te wezen een kroon moogt ontvangen.",
      "phraseDiff": [
        {
          "old": "gij",
          "new": "u",
          "principe": "A1"
        },
        {
          "old": "gij",
          "new": "u",
          "principe": "A1"
        },
        {
          "old": "zijt,",
          "new": "bent,",
          "principe": null
        }
      ],
      "grondtekst": [
        {
          "woord": "λαλεω",
          "lemma": "λαλέω"
        },
        {
          "woord": "πρεσβυτερος",
          "lemma": "πρεσβύτερος"
        },
        {
          "woord": "πρεπω",
          "lemma": "πρέπω"
        },
        {
          "woord": "γαρ",
          "lemma": "γάρ"
        },
        {
          "woord": "σοι",
          "lemma": "σοί"
        },
        {
          "woord": "εν",
          "lemma": "ἐν"
        },
        {
          "woord": "ακριβης",
          "lemma": "ἀκριβής"
        },
        {
          "woord": "επιστημη",
          "lemma": "ἐπιστήμη"
        },
        {
          "woord": "και",
          "lemma": "καί"
        },
        {
          "woord": "μη",
          "lemma": "μή"
        },
        {
          "woord": "εμποδιζω",
          "lemma": "ἐμποδίζω"
        },
        {
          "woord": "μουσικος",
          "lemma": "μουσικός"
        }
      ]
    },
    {
      "number": 4,
      "text1637": "Spreek, gij die oud zijt, want dat betaamt u, doch met ernstige wetenschap, en gij zult het snarenspel verhinderen.",
      "textSV1888": "Spreek, gij die oud zijt, want dat betaamt u, doch met ernstige wetenschap, en gij zult het snarenspel verhinderen.",
      "text2026": "Spreek, u die oud bent, want dat past u, maar met ernstige wetenschap, en u zult het snarenspel verhinderen.",
      "marginNotes": [],
      "text2026_html": "Spreek, u die oud bent, want dat past u, maar met ernstige wetenschap, en u zult het snarenspel verhinderen.",
      "phraseDiff": [
        {
          "old": "gij",
          "new": "u",
          "principe": "A1"
        },
        {
          "old": "zijt,",
          "new": "bent,",
          "principe": null
        },
        {
          "old": "betaamt",
          "new": "past",
          "principe": "V92"
        },
        {
          "old": "doch",
          "new": "maar",
          "principe": "V1"
        },
        {
          "old": "gij",
          "new": "u",
          "principe": "A1"
        }
      ],
      "grondtekst": [
        {
          "woord": "οπου",
          "lemma": "ὅπου"
        },
        {
          "woord": "ακροαμα",
          "lemma": "ἀκρόαμα"
        },
        {
          "woord": "μη",
          "lemma": "μή"
        },
        {
          "woord": "εκχεω",
          "lemma": "ἐκχέω"
        },
        {
          "woord": "λαλια",
          "lemma": "λαλιά"
        },
        {
          "woord": "και",
          "lemma": "καί"
        },
        {
          "woord": "ακαιρως",
          "lemma": "ἀκαίρως"
        },
        {
          "woord": "μη",
          "lemma": "μή"
        },
        {
          "woord": "σοφιζω",
          "lemma": "σοφίζω"
        }
      ]
    },
    {
      "number": 5,
      "text1637": "Waar men toeluistert, giet daar uw rede niet uit, en zijt niet wijs buiten tijds.",
      "textSV1888": "Waar men toeluistert, giet daar uw rede niet uit, en zijt niet wijs buiten tijds.",
      "text2026": "Waar men toeluistert, giet daar uw rede niet uit, en zijt niet wijs buiten tijds.",
      "marginNotes": [],
      "text2026_html": "Waar men toeluistert, giet daar uw rede niet uit, en zijt niet wijs buiten tijds.",
      "grondtekst": [
        {
          "woord": "σφραγις",
          "lemma": "σφραγίς"
        },
        {
          "woord": "ανθραξ",
          "lemma": "ἄνθραξ"
        },
        {
          "woord": "επι",
          "lemma": "ἐπί"
        },
        {
          "woord": "κοσμος",
          "lemma": "κόσμος"
        },
        {
          "woord": "χρυσεος",
          "lemma": "χρύσεος"
        },
        {
          "woord": "συγκριμα",
          "lemma": "σύγκριμα"
        },
        {
          "woord": "μουσικος",
          "lemma": "μουσικός"
        },
        {
          "woord": "εν",
          "lemma": "ἐν"
        },
        {
          "woord": "συμποσιον",
          "lemma": "συμπόσιον"
        },
        {
          "woord": "οινος",
          "lemma": "οἶνος"
        }
      ]
    },
    {
      "number": 6,
      "text1637": "De samenstemming der muzikanten in een wijngelag is gelijk een zegel van een karbonkel op een gulden sieraad.",
      "textSV1888": "De samenstemming der muzikanten in een wijngelag is gelijk een zegel van een karbonkel op een gulden sieraad.",
      "text2026": "De samenstemming van de muzikanten in een wijngelag is zoals een zegel van een karbonkel op een gulden sieraad.",
      "marginNotes": [],
      "text2026_html": "De samenstemming van de muzikanten in een wijngelag is zoals een zegel van een karbonkel op een gulden sieraad.",
      "phraseDiff": [
        {
          "old": "der",
          "new": "van de",
          "principe": "N2"
        },
        {
          "old": "gelijk",
          "new": "zoals",
          "principe": null
        }
      ],
      "grondtekst": [
        {
          "woord": "εν",
          "lemma": "ἐν"
        },
        {
          "woord": "κατασκευασμα",
          "lemma": "κατασκεύασμα"
        },
        {
          "woord": "χρυσεος",
          "lemma": "χρύσεος"
        },
        {
          "woord": "σφραγις",
          "lemma": "σφραγίς"
        },
        {
          "woord": "σμαραγδος",
          "lemma": "σμάραγδος"
        },
        {
          "woord": "μελος",
          "lemma": "μέλος"
        },
        {
          "woord": "μουσικος",
          "lemma": "μουσικός"
        },
        {
          "woord": "επι",
          "lemma": "ἐπί"
        },
        {
          "woord": "ηδυς",
          "lemma": "ἡδύς"
        },
        {
          "woord": "οινος",
          "lemma": "οἶνος"
        }
      ]
    },
    {
      "number": 7,
      "text1637": "Het gezang der muzikanten bij zoete wijn, is als een zegel in een smaragd op een gulden stuk werk.",
      "textSV1888": "Het gezang der muzikanten bij zoete wijn, is als een zegel in een smaragd op een gulden stuk werk.",
      "text2026": "Het gezang van de muzikanten bij zoete wijn, is als een zegel in een smaragd op een gulden stuk werk.",
      "marginNotes": [],
      "text2026_html": "Het gezang van de muzikanten bij zoete wijn, is als een zegel in een smaragd op een gulden stuk werk.",
      "phraseDiff": [
        {
          "old": "der",
          "new": "van de",
          "principe": "N2"
        }
      ],
      "grondtekst": [
        {
          "woord": "λαλεω",
          "lemma": "λαλέω"
        },
        {
          "woord": "νεανισκος",
          "lemma": "νεανίσκος"
        },
        {
          "woord": "ει",
          "lemma": "εἰ"
        },
        {
          "woord": "χρεια",
          "lemma": "χρεία"
        },
        {
          "woord": "σου",
          "lemma": "σοῦ"
        },
        {
          "woord": "μολις",
          "lemma": "μόλις"
        },
        {
          "woord": "δις",
          "lemma": "δίς"
        },
        {
          "woord": "εαν",
          "lemma": "ἐάν"
        },
        {
          "woord": "επερωταω",
          "lemma": "ἐπερωτάω"
        }
      ]
    },
    {
      "number": 8,
      "text1637": "Spreek gij jongeling, als het u van node is, en zulks nauwe lijks, indien gij tweemaal gevraagd wordt.",
      "textSV1888": "Spreek gij jongeling, als het u van node is, en zulks nauwe lijks, indien gij tweemaal gevraagd wordt.",
      "text2026": "Spreek u jongeling, als het u nodig is, en zulks nauwe lijks, als u tweemaal gevraagd wordt.",
      "marginNotes": [],
      "text2026_html": "Spreek u jongeling, als het u nodig is, en zulks nauwe lijks, als u tweemaal gevraagd wordt.",
      "phraseDiff": [
        {
          "old": "gij",
          "new": "u",
          "principe": "A1"
        },
        {
          "old": "van node",
          "new": "nodig",
          "principe": "O15"
        },
        {
          "old": "indien gij",
          "new": "als u",
          "principe": "V41"
        }
      ],
      "grondtekst": [
        {
          "woord": "κεφαλαιοω",
          "lemma": "κεφαλαιόω"
        },
        {
          "woord": "λογος",
          "lemma": "λόγος"
        },
        {
          "woord": "εν",
          "lemma": "ἐν"
        },
        {
          "woord": "ολιγος",
          "lemma": "ὀλίγος"
        },
        {
          "woord": "πολυς",
          "lemma": "πολύς"
        },
        {
          "woord": "γινομαι",
          "lemma": "γίνομαι"
        },
        {
          "woord": "ως.1",
          "lemma": "ὥς"
        },
        {
          "woord": "γινωσκω",
          "lemma": "γινώσκω"
        },
        {
          "woord": "και",
          "lemma": "καί"
        },
        {
          "woord": "αμα",
          "lemma": "ἅμα"
        },
        {
          "woord": "σιωπαω",
          "lemma": "σιωπάω"
        }
      ]
    },
    {
      "number": 9,
      "text1637": "Maak uw rede kort, zeg met weinig woorden veel; wees gelijk als een die verstaat en evenwel zwijgt.",
      "textSV1888": "Maak uw rede kort, zeg met weinig woorden veel; wees gelijk als een die verstaat en evenwel zwijgt.",
      "text2026": "Maak uw rede kort, zeg met weinig woorden veel; wees zoals als een die verstaat en evenwel zwijgt.",
      "marginNotes": [],
      "text2026_html": "Maak uw rede kort, zeg met weinig woorden veel; wees zoals als een die verstaat en evenwel zwijgt.",
      "phraseDiff": [
        {
          "old": "gelijk",
          "new": "zoals",
          "principe": null
        }
      ],
      "grondtekst": [
        {
          "woord": "εν",
          "lemma": "ἐν"
        },
        {
          "woord": "μεσος",
          "lemma": "μέσος"
        },
        {
          "woord": "μεγιστανες",
          "lemma": "μεγιστᾶνες"
        },
        {
          "woord": "μη",
          "lemma": "μή"
        },
        {
          "woord": "εξισαζω",
          "lemma": "ἐξισάζω"
        },
        {
          "woord": "και",
          "lemma": "καί"
        },
        {
          "woord": "ετερος",
          "lemma": "ἕτερος"
        },
        {
          "woord": "λεγω",
          "lemma": "λέγω"
        },
        {
          "woord": "μη",
          "lemma": "μή"
        },
        {
          "woord": "πολυς",
          "lemma": "πολύς"
        },
        {
          "woord": "αδολεσχεω",
          "lemma": "ἀδολεσχέω"
        }
      ]
    },
    {
      "number": 10,
      "text1637": "Zijnde onder de groten, maak u hun niet gelijk, en waar oude lieden zijn, heb niet veel gekakel.",
      "textSV1888": "Zijnde onder de groten, maak u hun niet gelijk, en waar oude lieden zijn, heb niet veel gekakel.",
      "text2026": "Zijnde onder de groten, maak u hun niet zoals, en waar oude mensen zijn, heb niet veel gekakel.",
      "marginNotes": [],
      "text2026_html": "Zijnde onder de groten, maak u hun niet zoals, en waar oude mensen zijn, heb niet veel gekakel.",
      "phraseDiff": [
        {
          "old": "gelijk,",
          "new": "zoals,",
          "principe": null
        },
        {
          "old": "lieden",
          "new": "mensen",
          "principe": "V10"
        }
      ],
      "grondtekst": [
        {
          "woord": "προ",
          "lemma": "πρό"
        },
        {
          "woord": "βροντη",
          "lemma": "βροντή"
        },
        {
          "woord": "κατασπευδω",
          "lemma": "κατασπεύδω"
        },
        {
          "woord": "αστραπη",
          "lemma": "ἀστραπή"
        },
        {
          "woord": "και",
          "lemma": "καί"
        },
        {
          "woord": "προ",
          "lemma": "πρό"
        },
        {
          "woord": "αισχυντηρος",
          "lemma": "αἰσχυντηρός"
        },
        {
          "woord": "προερχομαι",
          "lemma": "προέρχομαι"
        },
        {
          "woord": "χαρις",
          "lemma": "χάρις"
        }
      ]
    },
    {
      "number": 11,
      "text1637": "De bliksem gaat haast voor de donder heen, en voor een eerbaar mens gaat aangenaamheid.",
      "textSV1888": "De bliksem gaat haast voor de donder heen, en voor een eerbaar mens gaat aangenaamheid.",
      "text2026": "De bliksem gaat haast voor de donder heen, en voor een eerbaar mens gaat aangenaamheid.",
      "marginNotes": [],
      "text2026_html": "De bliksem gaat haast voor de donder heen, en voor een eerbaar mens gaat aangenaamheid.",
      "grondtekst": [
        {
          "woord": "εν",
          "lemma": "ἐν"
        },
        {
          "woord": "ωρα",
          "lemma": "ὥρα"
        },
        {
          "woord": "εξεγειρω",
          "lemma": "ἐξεγείρω"
        },
        {
          "woord": "και",
          "lemma": "καί"
        },
        {
          "woord": "μη",
          "lemma": "μή"
        },
        {
          "woord": "ουραγεω",
          "lemma": "οὐραγέω"
        },
        {
          "woord": "αποτρεχω",
          "lemma": "ἀποτρέχω"
        },
        {
          "woord": "εις",
          "lemma": "εἰς"
        },
        {
          "woord": "οικος",
          "lemma": "οἶκος"
        },
        {
          "woord": "και",
          "lemma": "καί"
        },
        {
          "woord": "μη",
          "lemma": "μή"
        },
        {
          "woord": "ραθυμεω",
          "lemma": "ῥᾳθυμέω"
        }
      ]
    },
    {
      "number": 12,
      "text1637": "Word bij tijds wakker, en zijt niet van de laatsten; loop heen naar huis, en vertraag niet.",
      "textSV1888": "Word bij tijds wakker, en zijt niet van de laatsten; loop heen naar huis, en vertraag niet.",
      "text2026": "Word bij tijds wakker, en zijt niet van de laatsten; loop heen naar huis, en vertraag niet.",
      "marginNotes": [],
      "text2026_html": "Word bij tijds wakker, en zijt niet van de laatsten; loop heen naar huis, en vertraag niet.",
      "grondtekst": [
        {
          "woord": "εκει",
          "lemma": "ἐκεῖ"
        },
        {
          "woord": "παιζω",
          "lemma": "παίζω"
        },
        {
          "woord": "και",
          "lemma": "καί"
        },
        {
          "woord": "ποιεω",
          "lemma": "ποιέω"
        },
        {
          "woord": "ο",
          "lemma": "ὁ"
        },
        {
          "woord": "ενθυμημα",
          "lemma": "ἐνθύμημα"
        },
        {
          "woord": "σου",
          "lemma": "σοῦ"
        },
        {
          "woord": "και",
          "lemma": "καί"
        },
        {
          "woord": "μη",
          "lemma": "μή"
        },
        {
          "woord": "αμαρτανω",
          "lemma": "ἁμαρτάνω"
        },
        {
          "woord": "λογος",
          "lemma": "λόγος"
        },
        {
          "woord": "υπερηφανος",
          "lemma": "ὑπερήφανος"
        }
      ]
    },
    {
      "number": 13,
      "text1637": "Speel aldaar, en doe wat gij voorgenomen hebt, maar niet met zonden en hovaardige woorden.",
      "textSV1888": "Speel aldaar, en doe wat gij voorgenomen hebt, maar niet met zonden en hovaardige woorden.",
      "text2026": "Speel daar, en doe wat u voorgenomen hebt, maar niet met zonden en hovaardige woorden.",
      "marginNotes": [],
      "text2026_html": "Speel daar, en doe wat u voorgenomen hebt, maar niet met zonden en hovaardige woorden.",
      "phraseDiff": [
        {
          "old": "aldaar,",
          "new": "daar,",
          "principe": "V36"
        },
        {
          "old": "gij",
          "new": "u",
          "principe": "A1"
        }
      ],
      "grondtekst": [
        {
          "woord": "και",
          "lemma": "καί"
        },
        {
          "woord": "επι",
          "lemma": "ἐπί"
        },
        {
          "woord": "ουτος",
          "lemma": "οὗτος"
        },
        {
          "woord": "ευλογεω",
          "lemma": "εὐλογέω"
        },
        {
          "woord": "ο",
          "lemma": "ὁ"
        },
        {
          "woord": "ποιεω",
          "lemma": "ποιέω"
        },
        {
          "woord": "σε.1",
          "lemma": "σέ"
        },
        {
          "woord": "και",
          "lemma": "καί"
        },
        {
          "woord": "μεθυω",
          "lemma": "μεθύω"
        },
        {
          "woord": "σε.1",
          "lemma": "σέ"
        },
        {
          "woord": "απο",
          "lemma": "ἀπό"
        },
        {
          "woord": "ο",
          "lemma": "ὁ"
        },
        {
          "woord": "αγαθος",
          "lemma": "ἀγαθός"
        },
        {
          "woord": "αυτος",
          "lemma": "αὐτός"
        }
      ]
    },
    {
      "number": 14,
      "text1637": "En dank hiervoor Hem die u gemaakt heeft, en u dronken maakt van zijn goederen.",
      "textSV1888": "En dank hiervoor Hem die u gemaakt heeft, en u dronken maakt van zijn goederen.",
      "text2026": "En dank hiervoor hem die u gemaakt heeft, en u dronken maakt van zijn goederen.",
      "marginNotes": [],
      "text2026_html": "En dank hiervoor hem die u gemaakt heeft, en u dronken maakt van zijn goederen.",
      "grondtekst": [
        {
          "woord": "ο",
          "lemma": "ὁ"
        },
        {
          "woord": "φοβεω",
          "lemma": "φοβέω"
        },
        {
          "woord": "κυριος",
          "lemma": "κύριος"
        },
        {
          "woord": "εκδεχομαι",
          "lemma": "ἐκδέχομαι"
        },
        {
          "woord": "παιδεια",
          "lemma": "παιδεία"
        },
        {
          "woord": "και",
          "lemma": "καί"
        },
        {
          "woord": "ο",
          "lemma": "ὁ"
        },
        {
          "woord": "ορθριζω",
          "lemma": "ὀρθρίζω"
        },
        {
          "woord": "ευρισκω",
          "lemma": "εὑρίσκω"
        },
        {
          "woord": "ευδοκια",
          "lemma": "εὐδοκία"
        }
      ],
      "phraseDiff": [
        {
          "old": "Hem",
          "new": "hem",
          "principe": null
        }
      ]
    },
    {
      "number": 15,
      "text1637": "Wie de Here vreest, die zal zijn onderwijzing aannemen, en die zich vroeg tot Hem maken, zullen vinden wat hun wel behaagt.",
      "textSV1888": "Wie de Here vreest, die zal zijn onderwijzing aannemen, en die zich vroeg tot Hem maken, zullen vinden wat hun wel behaagt.",
      "text2026": "Wie JAHWEH vreest, die zal zijn onderwijzing aannemen, en die zich vroeg tot Hem maken, zullen vinden wat hun wel behaagt.",
      "marginNotes": [],
      "text2026_html": "Wie JAHWEH vreest, die zal zijn onderwijzing aannemen, en die zich vroeg tot Hem maken, zullen vinden wat hun wel behaagt.",
      "phraseDiff": [
        {
          "old": "de Here",
          "new": "JAHWEH",
          "principe": "V280"
        }
      ],
      "grondtekst": [
        {
          "woord": "ο",
          "lemma": "ὁ"
        },
        {
          "woord": "ζητεω",
          "lemma": "ζητέω"
        },
        {
          "woord": "νομος.1",
          "lemma": "νόμος"
        },
        {
          "woord": "εμπιπλημι",
          "lemma": "ἐμπίπλημι"
        },
        {
          "woord": "αυτος",
          "lemma": "αὐτός"
        },
        {
          "woord": "και",
          "lemma": "καί"
        },
        {
          "woord": "ο",
          "lemma": "ὁ"
        },
        {
          "woord": "υποκρινομαι",
          "lemma": "ὑποκρίνομαι"
        },
        {
          "woord": "σκανδαλιζω",
          "lemma": "σκανδαλίζω"
        },
        {
          "woord": "εν",
          "lemma": "ἐν"
        },
        {
          "woord": "αυτος",
          "lemma": "αὐτός"
        }
      ]
    },
    {
      "number": 16,
      "text1637": "Wie de wet zoekt, die zal daarvan vervuld worden; maar wie geveinsd is, zal daaraan geërgerd worden.",
      "textSV1888": "Wie de wet zoekt, die zal daarvan vervuld worden; maar wie geveinsd is, zal daaraan geërgerd worden.",
      "text2026": "Wie de wet zoekt, die zal daarvan vervuld worden; maar wie geveinsd is, zal daaraan geërgerd worden.",
      "marginNotes": [],
      "text2026_html": "Wie de wet zoekt, die zal daarvan vervuld worden; maar wie geveinsd is, zal daaraan geërgerd worden.",
      "grondtekst": [
        {
          "woord": "ο",
          "lemma": "ὁ"
        },
        {
          "woord": "φοβεω",
          "lemma": "φοβέω"
        },
        {
          "woord": "κυριος",
          "lemma": "κύριος"
        },
        {
          "woord": "ευρισκω",
          "lemma": "εὑρίσκω"
        },
        {
          "woord": "κριμα",
          "lemma": "κρίμα"
        },
        {
          "woord": "και",
          "lemma": "καί"
        },
        {
          "woord": "δικαιωμα",
          "lemma": "δικαίωμα"
        },
        {
          "woord": "ως.1",
          "lemma": "ὥς"
        },
        {
          "woord": "φως",
          "lemma": "φῶς"
        },
        {
          "woord": "εξαπτω",
          "lemma": "ἐξάπτω"
        }
      ]
    },
    {
      "number": 17,
      "text1637": "Die de Here vrezen, zullen vinden dat recht is, en zullen gerechtigheden aansteken als een licht.",
      "textSV1888": "Die de Here vrezen, zullen vinden dat recht is, en zullen gerechtigheden aansteken als een licht.",
      "text2026": "Die JAHWEH vrezen, zullen vinden dat recht is, en zullen gerechtigheden aansteken als een licht.",
      "marginNotes": [],
      "text2026_html": "Die JAHWEH vrezen, zullen vinden dat recht is, en zullen gerechtigheden aansteken als een licht.",
      "phraseDiff": [
        {
          "old": "de Here",
          "new": "JAHWEH",
          "principe": "V280"
        }
      ],
      "grondtekst": [
        {
          "woord": "ανθρωπος",
          "lemma": "ἄνθρωπος"
        },
        {
          "woord": "αμαρτωλος",
          "lemma": "ἁμαρτωλός"
        },
        {
          "woord": "εκκλινω",
          "lemma": "ἐκκλίνω"
        },
        {
          "woord": "ελεγμος",
          "lemma": "ἐλεγμός"
        },
        {
          "woord": "και",
          "lemma": "καί"
        },
        {
          "woord": "κατα",
          "lemma": "κατά"
        },
        {
          "woord": "ο",
          "lemma": "ὁ"
        },
        {
          "woord": "θελημα",
          "lemma": "θέλημα"
        },
        {
          "woord": "αυτος",
          "lemma": "αὐτός"
        },
        {
          "woord": "ευρισκω",
          "lemma": "εὑρίσκω"
        },
        {
          "woord": "συγκριμα",
          "lemma": "σύγκριμα"
        }
      ]
    },
    {
      "number": 18,
      "text1637": "Een goddeloos mens ontwijkt de bestraffing, en naar zijn wil vindt hij uit hetgeen hem behaagt.",
      "textSV1888": "Een goddeloos mens ontwijkt de bestraffing, en naar zijn wil vindt hij uit hetgeen hem behaagt.",
      "text2026": "Een goddeloos mens ontwijkt de bestraffing, en naar zijn wil vindt hij uit wat hem behaagt.",
      "marginNotes": [],
      "text2026_html": "Een goddeloos mens ontwijkt de bestraffing, en naar zijn wil vindt hij uit wat hem behaagt.",
      "phraseDiff": [
        {
          "old": "hetgeen",
          "new": "wat",
          "principe": "V4"
        }
      ],
      "grondtekst": [
        {
          "woord": "ανηρ",
          "lemma": "ἀνήρ"
        },
        {
          "woord": "βουλη",
          "lemma": "βουλή"
        },
        {
          "woord": "ου",
          "lemma": "οὐ"
        },
        {
          "woord": "μη",
          "lemma": "μή"
        },
        {
          "woord": "παρειδον",
          "lemma": "παρεῖδον"
        },
        {
          "woord": "διανοημα",
          "lemma": "διανόημα"
        },
        {
          "woord": "αλλοτριος",
          "lemma": "ἀλλότριος"
        },
        {
          "woord": "και",
          "lemma": "καί"
        },
        {
          "woord": "υπερηφανος",
          "lemma": "ὑπερήφανος"
        },
        {
          "woord": "ου",
          "lemma": "οὐ"
        },
        {
          "woord": "καταπτησσω",
          "lemma": "καταπτήσσω"
        },
        {
          "woord": "φοβος",
          "lemma": "φόβος"
        }
      ]
    },
    {
      "number": 19,
      "text1637": "Een welberaden man veracht de bedenking niet, maar een vreemde en hovaardige is voor vrees niet vervaard, en nadat hij iets gedaan heeft, is hij bij zichzelf zonder raad.",
      "textSV1888": "Een welberaden man veracht de bedenking niet, maar een vreemde en hovaardige is voor vrees niet vervaard, en nadat hij iets gedaan heeft, is hij bij zichzelf zonder raad.",
      "text2026": "Een welberaden man veracht de bedenking niet, maar een vreemde en hovaardige is voor vrees niet vervaard, en nadat hij iets gedaan heeft, is hij bij zichzelf zonder raad.",
      "marginNotes": [],
      "text2026_html": "Een welberaden man veracht de bedenking niet, maar een vreemde en hovaardige is voor vrees niet vervaard, en nadat hij iets gedaan heeft, is hij bij zichzelf zonder raad.",
      "grondtekst": [
        {
          "woord": "ανευ",
          "lemma": "ἄνευ"
        },
        {
          "woord": "βουλη",
          "lemma": "βουλή"
        },
        {
          "woord": "μηδεις",
          "lemma": "μηδείς"
        },
        {
          "woord": "ποιεω",
          "lemma": "ποιέω"
        },
        {
          "woord": "και",
          "lemma": "καί"
        },
        {
          "woord": "εν",
          "lemma": "ἐν"
        },
        {
          "woord": "ο",
          "lemma": "ὁ"
        },
        {
          "woord": "ποιεω",
          "lemma": "ποιέω"
        },
        {
          "woord": "σε.1",
          "lemma": "σέ"
        },
        {
          "woord": "μη",
          "lemma": "μή"
        },
        {
          "woord": "μεταμελομαι",
          "lemma": "μεταμέλομαι"
        }
      ]
    },
    {
      "number": 20,
      "text1637": "Doe niets zonder raad, en als gij het gedaan hebt, laat het u niet berouwen.",
      "textSV1888": "Doe niets zonder raad, en als gij het gedaan hebt, laat het u niet berouwen.",
      "text2026": "Doe niets zonder raad, en als u het gedaan hebt, laat het u niet berouwen.",
      "marginNotes": [],
      "text2026_html": "Doe niets zonder raad, en als u het gedaan hebt, laat het u niet berouwen.",
      "phraseDiff": [
        {
          "old": "gij",
          "new": "u",
          "principe": "A1"
        }
      ],
      "grondtekst": [
        {
          "woord": "εν",
          "lemma": "ἐν"
        },
        {
          "woord": "οδος",
          "lemma": "ὁδός"
        },
        {
          "woord": "αντιπτωμα",
          "lemma": "ἀντίπτωμα"
        },
        {
          "woord": "μη",
          "lemma": "μή"
        },
        {
          "woord": "πορευομαι",
          "lemma": "πορεύομαι"
        },
        {
          "woord": "και",
          "lemma": "καί"
        },
        {
          "woord": "μη",
          "lemma": "μή"
        },
        {
          "woord": "προσκοπτω",
          "lemma": "προσκόπτω"
        },
        {
          "woord": "εν",
          "lemma": "ἐν"
        },
        {
          "woord": "λιθωδης",
          "lemma": "λιθώδης"
        }
      ]
    },
    {
      "number": 21,
      "text1637": "Ga niet op de weg waarop men lichtelijk valt, en gij zult tegen geen steenachtige plaatsen aanstoten.",
      "textSV1888": "Ga niet op de weg waarop men lichtelijk valt, en gij zult tegen geen steenachtige plaatsen aanstoten.",
      "text2026": "Ga niet op de weg waarop men licht valt, en u zult tegen geen steenachtige plaatsen aanstoten.",
      "marginNotes": [],
      "text2026_html": "Ga niet op de weg waarop men licht valt, en u zult tegen geen steenachtige plaatsen aanstoten.",
      "phraseDiff": [
        {
          "old": "lichtelijk",
          "new": "licht",
          "principe": "V154"
        },
        {
          "old": "gij",
          "new": "u",
          "principe": "A1"
        }
      ],
      "grondtekst": [
        {
          "woord": "μη",
          "lemma": "μή"
        },
        {
          "woord": "πιστευω",
          "lemma": "πιστεύω"
        },
        {
          "woord": "εν",
          "lemma": "ἐν"
        },
        {
          "woord": "οδος",
          "lemma": "ὁδός"
        },
        {
          "woord": "απροσκοπος",
          "lemma": "ἀπρόσκοπος"
        }
      ]
    },
    {
      "number": 22,
      "text1637": "Vertrouw op de weg niet, die zonder aanstoot is, en wacht u voor uw kinderen.",
      "textSV1888": "Vertrouw op de weg niet, die zonder aanstoot is, en wacht u voor uw kinderen.",
      "text2026": "Vertrouw op de weg niet, die zonder aanstoot is, en wacht u voor uw kinderen.",
      "marginNotes": [],
      "text2026_html": "Vertrouw op de weg niet, die zonder aanstoot is, en wacht u voor uw kinderen.",
      "grondtekst": [
        {
          "woord": "και",
          "lemma": "καί"
        },
        {
          "woord": "απο",
          "lemma": "ἀπό"
        },
        {
          "woord": "ο",
          "lemma": "ὁ"
        },
        {
          "woord": "τεκνον",
          "lemma": "τέκνον"
        },
        {
          "woord": "σου",
          "lemma": "σοῦ"
        },
        {
          "woord": "φυλασσω",
          "lemma": "φυλάσσω"
        }
      ]
    },
    {
      "number": 23,
      "text1637": "Vertrouw uzelf in alle goede werken, want ook dat is een onderhouding der geboden.",
      "textSV1888": "Vertrouw uzelf in alle goede werken, want ook dat is een onderhouding der geboden.",
      "text2026": "Vertrouw uzelf in alle goede werken, want ook dat is een onderhouding van de geboden.",
      "marginNotes": [],
      "text2026_html": "Vertrouw uzelf in alle goede werken, want ook dat is een onderhouding van de geboden.",
      "phraseDiff": [
        {
          "old": "der",
          "new": "van de",
          "principe": "N2"
        }
      ],
      "grondtekst": [
        {
          "woord": "εν",
          "lemma": "ἐν"
        },
        {
          "woord": "πας",
          "lemma": "πᾶς"
        },
        {
          "woord": "εργον",
          "lemma": "ἔργον"
        },
        {
          "woord": "πιστευω",
          "lemma": "πιστεύω"
        },
        {
          "woord": "ο",
          "lemma": "ὁ"
        },
        {
          "woord": "ψυχη",
          "lemma": "ψυχή"
        },
        {
          "woord": "σου",
          "lemma": "σοῦ"
        },
        {
          "woord": "και",
          "lemma": "καί"
        },
        {
          "woord": "γαρ",
          "lemma": "γάρ"
        },
        {
          "woord": "ουτος",
          "lemma": "οὗτος"
        },
        {
          "woord": "ειμι",
          "lemma": "εἰμί"
        },
        {
          "woord": "τηρησις",
          "lemma": "τήρησις"
        },
        {
          "woord": "εντολη",
          "lemma": "ἐντολή"
        }
      ]
    },
    {
      "number": 24,
      "text1637": "Wie de Here gelooft, die let op het gebod, en wie zijn betrouwen op hem zet, die zal geen gebrek hebben.",
      "textSV1888": "Wie de Here gelooft, die let op het gebod, en wie zijn betrouwen op hem zet, die zal geen gebrek hebben.",
      "text2026": "Wie JAHWEH gelooft, die let op het gebod, en wie zijn betrouwen op Hem zet, die zal geen gebrek hebben.",
      "marginNotes": [],
      "text2026_html": "Wie JAHWEH gelooft, die let op het gebod, en wie zijn betrouwen op Hem zet, die zal geen gebrek hebben.",
      "phraseDiff": [
        {
          "old": "de Here",
          "new": "JAHWEH",
          "principe": "V280"
        },
        {
          "old": "hem",
          "new": "Hem",
          "principe": null
        }
      ],
      "grondtekst": [
        {
          "woord": "ο",
          "lemma": "ὁ"
        },
        {
          "woord": "πιστευω",
          "lemma": "πιστεύω"
        },
        {
          "woord": "νομος.1",
          "lemma": "νόμος"
        },
        {
          "woord": "προσεχω",
          "lemma": "προσέχω"
        },
        {
          "woord": "εντολη",
          "lemma": "ἐντολή"
        },
        {
          "woord": "και",
          "lemma": "καί"
        },
        {
          "woord": "ο",
          "lemma": "ὁ"
        },
        {
          "woord": "πειθω",
          "lemma": "πείθω"
        },
        {
          "woord": "κυριος",
          "lemma": "κύριος"
        },
        {
          "woord": "ου",
          "lemma": "οὐ"
        },
        {
          "woord": "ελαττοω",
          "lemma": "ἐλαττόω"
        }
      ]
    }
  ],
  "chapterIntro": {
    "text1637": "1 Hoe een oudt ende aensienlick man hem moet houden in het spreken aen een tafel. 8 Hoe een jongelingh in het stil swijgen, 12 ende in tijts na huys te gaen. 15 Een vroom man heeft de onderwijsinge lief, 18 maer een godtloose haet deselve. 20 In al ons doen moeten wy op Godts gebodt, ende goeden raet letten, 23 ende den Heere betrouwen."
  }
}